README.md
setup.py
Extended_BoxPlots.egg-info/PKG-INFO
Extended_BoxPlots.egg-info/SOURCES.txt
Extended_BoxPlots.egg-info/dependency_links.txt
Extended_BoxPlots.egg-info/requires.txt
Extended_BoxPlots.egg-info/top_level.txt
extended_boxplots/__init__.py
extended_boxplots/extended_boxplot.py