Metadata-Version: 2.1
Name: Extended-BoxPlots
Version: 0.2.0
Summary: Generator of extended box plots
Home-page: https://github.com/dmey/extended-boxplots
Author: dmey
Author-email: dmey@users.noreply.github.com
License: MIT
Keywords: graph,plottings,statistics
Platform: Windows
Platform: Linux
Platform: Solaris
Platform: Mac OS-X
Platform: Unix
Requires-Python: >=3.5
